thelittlehackers/__init__.py
thelittlehackers/constant/__init__.py
thelittlehackers/constant/contact.py
thelittlehackers/constant/data_type.py
thelittlehackers/constant/entity.py
thelittlehackers/constant/locale.py
thelittlehackers/constant/logging.py
thelittlehackers/constant/privacy.py
thelittlehackers/constant/regex.py
thelittlehackers/constant/sort_order.py
thelittlehackers/model/__init__.py
thelittlehackers/model/contact.py
thelittlehackers/model/country.py
thelittlehackers/model/locale.py
thelittlehackers/model/version.py
thelittlehackers/utils/__init__.py
thelittlehackers/utils/any_utils.py
thelittlehackers/utils/logging_utils.py
thelittlehackers/utils/mapping_utils.py
thelittlehackers/utils/module_utils.py
thelittlehackers/utils/string_utils.py
thelittlehackers_core-1.0.9.dist-info/LICENSE.md
thelittlehackers_core-1.0.9.dist-info/METADATA
thelittlehackers_core-1.0.9.dist-info/WHEEL
thelittlehackers_core-1.0.9.dist-info/RECORD
